django_tml/__init__.py
django_tml/fields.py
django_tml/middleware.py
django_tml/tml_cookies.py
django_tml/translator.py
django_tml/management/__init__.py
django_tml/management/commands/__init__.py
django_tml/management/commands/tml_cache.py
django_tml/templates/__init__.py
django_tml/templates/django_tml/inline_translations/footer.html
django_tml/templates/django_tml/inline_translations/header.html
django_tml/templates/django_tml/inline_translations/language_selector.html
django_tml/templatetags/__init__.py
django_tml/templatetags/tml.py
django_tml/templatetags/tml_inline.py
django_tml-0.3.1.dist-info/DESCRIPTION.rst
django_tml-0.3.1.dist-info/METADATA
django_tml-0.3.1.dist-info/metadata.json
django_tml-0.3.1.dist-info/RECORD
django_tml-0.3.1.dist-info/top_level.txt
django_tml-0.3.1.dist-info/WHEEL
